idta/Drug_module.py
idta/__init__.py
idta-0.1.1.dist-info/LICENSE.md
idta-0.1.1.dist-info/METADATA
idta-0.1.1.dist-info/WHEEL
idta-0.1.1.dist-info/top_level.txt
idta-0.1.1.dist-info/RECORD
