Metadata-Version: 2.1
Name: idta
Version: 0.1.1
Summary: Inhibitory Drug Target Analyser
Author: Faruk Üstünel
Author-email: <faruk.ustunel@bezmialem.edu.tr>
Keywords: drug target,viruses
Classifier: Development Status :: 3 - Alpha
Classifier: Intended Audience :: Science/Research
Classifier: Intended Audience :: Healthcare Industry
Classifier: Programming Language :: Python :: 3
Classifier: Operating System :: Unix
License-File: LICENSE.md
Requires-Dist: biopython
Requires-Dist: pandas
Requires-Dist: numpy
Requires-Dist: nglview
